LICENSE
README.md
setup.py
kolmov/__init__.py
kolmov/crossval_fit_table.py
kolmov/crossval_table.py
kolmov/fit_table.py
kolmov.egg-info/PKG-INFO
kolmov.egg-info/SOURCES.txt
kolmov.egg-info/dependency_links.txt
kolmov.egg-info/requires.txt
kolmov.egg-info/top_level.txt
kolmov/utils/__init__.py
kolmov/utils/constants.py
kolmov/utils/legacy_exports.py
kolmov/utils/plot_functions.py
kolmov/utils/utils.py