Metadata-Version: 2.1
Name: kolmov
Version: 2.0.5
Summary: A Framework for performing cross validation for Ringer tunings
Home-page: https://github.com/micaelverissimo/kolmov
Author: Micael Veríssimo de Araújo, Gabriel Gazola Milan, João Victor da Fonseca Pinto
Author-email: micael.verissimo@lps.ufrj.br, gabriel.milan@lps.ufrj.br, jodafons@lps.ufrj.br
License: GPL-3.0
Keywords: framework,validation,machine-learning,ai,plotting,data-visualization
Platform: UNKNOWN
Classifier: Development Status :: 4 - Beta
Classifier: Intended Audience :: Developers
Classifier: Topic :: Software Development :: Libraries :: Python Modules
Classifier: License :: OSI Approved :: GNU General Public License v3 (GPLv3)
Classifier: Programming Language :: Python :: 3
Classifier: Programming Language :: Python :: 3.7
Classifier: Programming Language :: Python :: 3.8
